setup.py
distributions_probability_xyz/Binomialdistribution.py
distributions_probability_xyz/Gaussian_distribution.py
distributions_probability_xyz/General_distribution.py
distributions_probability_xyz/__init__.py
distributions_probability_xyz.egg-info/PKG-INFO
distributions_probability_xyz.egg-info/SOURCES.txt
distributions_probability_xyz.egg-info/dependency_links.txt
distributions_probability_xyz.egg-info/not-zip-safe
distributions_probability_xyz.egg-info/top_level.txt