Metadata-Version: 2.1
Name: distributions-probability-xyz
Version: 1.2
Summary: Gaussian and Binomial distributions
Author: Pushpita Das
Author-email: pushpita05102002@gmail.com
